setup.py
framsreader/__init__.py
framsreader/_all.py
framsreader/framscript.xml
framsreader.egg-info/PKG-INFO
framsreader.egg-info/SOURCES.txt
framsreader.egg-info/dependency_links.txt
framsreader.egg-info/top_level.txt