Metadata-Version: 1.1
Name: framsreader
Version: 0.1.1
Summary: Files parser for Framsticks.
Home-page: UNKNOWN
Author: Michał Kempka
Author-email: kempka.michal@gmail.com
License: UNKNOWN
Keywords: framsticks
Platform: UNKNOWN
Classifier: Development Status :: 4 - Beta
Classifier: Intended Audience :: Science/Research
Classifier: Topic :: Scientific/Engineering :: Artificial Intelligence
Classifier: License :: OSI Approved :: MIT License
Classifier: Programming Language :: Python :: 3.4
Classifier: Programming Language :: Python :: 3.5
